README.rst
setup.py
supervisorc/__init__.py
supervisorc/process.py
supervisorc/supervisor.py
supervisorc.egg-info/PKG-INFO
supervisorc.egg-info/SOURCES.txt
supervisorc.egg-info/dependency_links.txt
supervisorc.egg-info/top_level.txt