Metadata-Version: 1.1
Name: supervisorc
Version: 0.1.0
Summary: A high level api for XML-RPC supervisor server
Home-page: https://github.com/gisce/supervisorc
Author: GISCE-TI, S.L.
Author-email: devel@gisce.net
License: MIT
Platform: UNKNOWN
Classifier: Programming Language :: Python :: 2.7
Classifier: Programming Language :: Python :: 3.5
Classifier: Topic :: Software Development :: Libraries
